postgresimporter/__init__.py
postgresimporter/cli.py
postgresimporter/csvcount.py
postgresimporter/exec.py
postgresimporter/import.py
postgresimporter/main.py
postgresimporter/utils.py
postgresimporter-1.0.1.dist-info/LICENSE
postgresimporter-1.0.1.dist-info/METADATA
postgresimporter-1.0.1.dist-info/WHEEL
postgresimporter-1.0.1.dist-info/entry_points.txt
postgresimporter-1.0.1.dist-info/top_level.txt
postgresimporter-1.0.1.dist-info/RECORD
